valiant/__about__.py
valiant/__init__.py
valiant/__main__.py
valiant/__version__.py
valiant/config/__init__.py
valiant/config/builder.py
valiant/config/config.py
valiant/config/default_builder.py
valiant/config/source/__init__.py
valiant/config/source/map.py
valiant/config/source/toml.py
valiant/config/util.py
valiant/console/__init__.py
valiant/console/cli.py
valiant/console/commands/__init__.py
valiant/console/commands/about.py
valiant/console/commands/audit.py
valiant/console/commands/base_command.py
valiant/console/commands/config.py
valiant/console/commands/package_command.py
valiant/console/commands/report.py
valiant/console/commands/report_helper.py
valiant/console/commands/show.py
valiant/console/config/__init__.py
valiant/console/config/application_config.py
valiant/exceptions.py
valiant/log/__init__.py
valiant/package/__init__.py
valiant/package/classifier.py
valiant/package/model.py
valiant/plugins/FLAKE8_LICENCE
valiant/plugins/__init__.py
valiant/plugins/exceptions.py
valiant/plugins/manager.py
valiant/plugins/plugin.py
valiant/plugins/reports/__init__.py
valiant/plugins/reports/basic/README.md
valiant/plugins/reports/basic/__init__.py
valiant/plugins/reports/basic/provider.py
valiant/plugins/reports/demo.py
valiant/plugins/reports/report.py
valiant/plugins/reports/safety/README.md
valiant/plugins/reports/safety/__init__.py
valiant/plugins/reports/safety/provider.py
valiant/plugins/reports/spdx/README.md
valiant/plugins/reports/spdx/__init__.py
valiant/plugins/reports/spdx/__main__.py
valiant/plugins/reports/spdx/license.py
valiant/plugins/reports/spdx/provider.py
valiant/plugins/reports/spdx/spdx-licenses.pickle
valiant/plugins/type_manager.py
valiant/reports/__init__.py
valiant/reports/model.py
valiant/repositories/__init__.py
valiant/repositories/config.py
valiant/repositories/exceptions.py
valiant/repositories/factory.py
valiant/repositories/pypi/__init__.py
valiant/repositories/pypi/model.py
valiant/repositories/pypi/pypi.py
valiant-0.2.3.dist-info/entry_points.txt
valiant-0.2.3.dist-info/LICENSE
valiant-0.2.3.dist-info/WHEEL
valiant-0.2.3.dist-info/METADATA
valiant-0.2.3.dist-info/RECORD
