Metadata-Version: 2.1
Name: valiant
Version: 0.2.3
Summary: Audit tool to help investigate Python dependencies
Home-page: https://github.com/pomes/valiant
License: MIT
Keywords: audit,dependency,bom
Author: Duncan Dickinson
Author-email: dedickinson@users.noreply.github.com
Maintainer: Duncan Dickinson
Maintainer-email: dedickinson@users.noreply.github.com
Requires-Python: >=3.8,<3.10
Classifier: Development Status :: 1 - Planning
Classifier: Environment :: Console
Classifier: Intended Audience :: Developers
Classifier: License :: OSI Approved :: MIT License
Classifier: Programming Language :: Python :: 3
Classifier: Programming Language :: Python :: 3.8
Classifier: Programming Language :: Python :: 3.9
Classifier: Topic :: Security
Classifier: Topic :: Software Development
Classifier: Topic :: Software Development :: Quality Assurance
Classifier: Topic :: System :: Software Distribution
Requires-Dist: appdirs (>=1.4.3,<2.0.0)
Requires-Dist: cleo (>=0.7.6,<0.8.0)
Requires-Dist: desert (>=2020.1.6,<2021.0.0)
Requires-Dist: marshmallow (>=3.5.1,<4.0.0)
Requires-Dist: marshmallow-dataclass (>=7.5.2,<8.0.0)
Requires-Dist: requests (>=2.23.0,<3.0.0)
Requires-Dist: requests-cache (>=0.5.2,<0.6.0)
Requires-Dist: safety (>=1.8.7,<2.0.0)
Requires-Dist: setuptools (>=46.0.0,<47.0.0)
Requires-Dist: structlog (>=20.1.0,<21.0.0)
Requires-Dist: texttable (>=1.6.2,<2.0.0)
Requires-Dist: wcwidth (>=0.1.8,<0.2.0)
Project-URL: Documentation, https://pomes.github.io/valiant/
Project-URL: Issue tracker, https://github.com/pomes/valiant/issues
Project-URL: Repository, https://github.com/pomes/valiant
